anvil-stubs/__init__.pyi
anvil-stubs/tables/__init__.pyi
anvil-stubs/tables/table.pyi
anvil_stubs-0.0.1.dist-info/LICENSE
anvil_stubs-0.0.1.dist-info/METADATA
anvil_stubs-0.0.1.dist-info/WHEEL
anvil_stubs-0.0.1.dist-info/top_level.txt
anvil_stubs-0.0.1.dist-info/RECORD
