Metadata-Version: 2.1
Name: anvil-stubs
Version: 0.0.1
License-File: LICENSE
Requires-Dist: anvil-uplink
